wekapyutils/__init__.py
wekapyutils/_version.py
wekapyutils/announce.py
wekapyutils/circular_list.py
wekapyutils/pushd.py
wekapyutils/sthreads.py
wekapyutils/unit_test.py
wekapyutils/wekalogging.py
wekapyutils/wekassh.py
wekapyutils/wekatime.py
wekapyutils-1.0.18.dist-info/licenses/LICENSE
wekapyutils-1.0.18.dist-info/METADATA
wekapyutils-1.0.18.dist-info/WHEEL
wekapyutils-1.0.18.dist-info/top_level.txt
wekapyutils-1.0.18.dist-info/RECORD
